LICENSE.txt
MANIFEST.in
README.rst
requirements-test.txt
setup.py
jsonrpc_base/__init__.py
jsonrpc_base/jsonrpc.py
jsonrpc_base.egg-info/PKG-INFO
jsonrpc_base.egg-info/SOURCES.txt
jsonrpc_base.egg-info/dependency_links.txt
jsonrpc_base.egg-info/top_level.txt