Metadata-Version: 1.1
Name: jsonrpc-base
Version: 1.0.3
Summary: A JSON-RPC client library base interface
Home-page: http://github.com/armills/jsonrpc-base
Author: Adam Mills
Author-email: adam@armills.info
License: BSD
Keywords: json-rpc base
Platform: UNKNOWN
Classifier: Development Status :: 5 - Production/Stable
Classifier: Intended Audience :: Developers
Classifier: Topic :: Software Development :: Libraries
Classifier: License :: OSI Approved :: BSD License
Classifier: Programming Language :: Python :: 3
Classifier: Programming Language :: Python :: 3.5
Classifier: Programming Language :: Python :: 3.6
Classifier: Programming Language :: Python :: 3.7
Classifier: Programming Language :: Python :: 3.8
